setup.py
hkit/__init__.py
hkit/dbutil.py
hkit/dtutil.py
hkit.egg-info/PKG-INFO
hkit.egg-info/SOURCES.txt
hkit.egg-info/dependency_links.txt
hkit.egg-info/top_level.txt
tests/__init__.py
tests/test_dtutil.py