Metadata-Version: 2.1
Name: hkit
Version: 1.0.6
Summary: simple tools for daily use
Home-page: https://404.com
Author: huangweiwei
Author-email: geverway@gmail.com
License: UNKNOWN
Platform: UNKNOWN
Classifier: Programming Language :: Python :: 3
Classifier: License :: OSI Approved :: MIT License
Classifier: Operating System :: OS Independent
Requires-Python: >=3.6
